contentstack_utils/__init__.py
contentstack_utils/automate.py
contentstack_utils/gql.py
contentstack_utils/utils.py
contentstack_utils/embedded/__init__.py
contentstack_utils/embedded/item_type.py
contentstack_utils/embedded/styletype.py
contentstack_utils/helper/__init__.py
contentstack_utils/helper/converter.py
contentstack_utils/helper/metadata.py
contentstack_utils/helper/node_to_html.py
contentstack_utils/render/__init__.py
contentstack_utils/render/options.py
contentstack_utils-1.3.3.dist-info/licenses/LICENSE
tests/__init__.py
tests/convert_style.py
tests/test_default_opt_others.py
tests/test_gql_to_html_func.py
tests/test_helper_node_to_html.py
tests/test_item_types.py
tests/test_metadata.py
tests/test_option_render_mark.py
tests/test_render_default_options.py
tests/test_render_options.py
tests/test_style_type.py
tests/test_util_srte.py
tests/test_utils.py
contentstack_utils-1.3.3.dist-info/METADATA
contentstack_utils-1.3.3.dist-info/WHEEL
contentstack_utils-1.3.3.dist-info/top_level.txt
contentstack_utils-1.3.3.dist-info/RECORD
